mdocLib/__init__.py
mdocLib/mdoc.py
mdocLib/__pycache__/__init__.cpython-312.opt-1.pyc
mdocLib/__pycache__/__init__.cpython-312.opt-2.pyc
mdocLib/__pycache__/__init__.cpython-312.pyc
mdocLib/__pycache__/mdoc.cpython-312.opt-1.pyc
mdocLib/__pycache__/mdoc.cpython-312.opt-2.pyc
mdocLib/__pycache__/mdoc.cpython-312.pyc
mdocLib-0.0.2.dist-info/LICENSE
mdocLib-0.0.2.dist-info/METADATA
mdocLib-0.0.2.dist-info/WHEEL
mdocLib-0.0.2.dist-info/top_level.txt
mdocLib-0.0.2.dist-info/RECORD
